locatr/__init__.py
locatr/_constants.py
locatr/_locatr.py
locatr/_utils.py
locatr/exceptions.py
locatr/schema.py
locatr/bin/locatr.bin
test_locatr-0.56.2.dist-info/METADATA
test_locatr-0.56.2.dist-info/WHEEL
test_locatr-0.56.2.dist-info/licenses/LICENSE
test_locatr-0.56.2.dist-info/RECORD
