Metadata-Version: 2.4
Name: test_locatr
Version: 0.56.2
Summary: Get HTML/XML elements css/xpath selectors using natural language.
Author-email: Neeraj319 <neeraj@vertexcover.io>
License-Expression: MIT
License-File: LICENSE
Requires-Python: >=3.9
Requires-Dist: pydantic>=2.10.4
